file_editor/__init__.py
file_editor/editor.py
file_editor-1.0.0.dist-info/DESCRIPTION.rst
file_editor-1.0.0.dist-info/METADATA
file_editor-1.0.0.dist-info/RECORD
file_editor-1.0.0.dist-info/WHEEL
file_editor-1.0.0.dist-info/metadata.json
file_editor-1.0.0.dist-info/top_level.txt
