Metadata-Version: 2.0
Name: file-editor
Version: 1.0.0
Summary: A python package to convert a image/pdf file to pdf/image file format
Home-page: https://github.com/nikhilkumarsingh/weather-reporter
Author: Manchikanti Santhosh
Author-email: manchikantisanthosh@gmail.com
License: MIT
Platform: UNKNOWN
Classifier: License :: OSI Approved :: MIT License
Classifier: Programming Language :: Python :: 2.7
Classifier: Programming Language :: Python :: 3
Classifier: Programming Language :: Python :: 3.7
Requires-Dist: pdf2image
